COPYING
README.txt
setup.py
PlotKit.egg-info/SOURCES.txt
plotkit/__init__.py
plotkit/release.py
plotkit/widgets.py
plotkit.egg-info/PKG-INFO
plotkit.egg-info/SOURCES.txt
plotkit.egg-info/entry_points.txt
plotkit.egg-info/paster_plugins.txt
plotkit.egg-info/requires.txt
plotkit.egg-info/sqlobject.txt
plotkit.egg-info/top_level.txt
plotkit/static/javascript/Base.js
plotkit/static/javascript/Canvas.js
plotkit/static/javascript/EasyPlot.js
plotkit/static/javascript/Layout.js
plotkit/static/javascript/PlotKit.js
plotkit/static/javascript/PlotKit_Packed.js
plotkit/static/javascript/SVG.js
plotkit/static/javascript/SweetCanvas.js
plotkit/static/javascript/SweetSVG.js
plotkit/static/javascript/dummy.svg
plotkit/static/javascript/excanvas.js
plotkit/templates/__init__.py
