Metadata-Version: 1.0
Name: PlotKit
Version: 0.9.1w3
Summary: PlotKit packaged as TurboGears widgets.
Home-page: http://sourceforge.net/projects/tgwidgets
Author: Fred Lin
Author-email: gasolin+tg@gmail.com
License: BSD
Download-URL: http://optusnet.dl.sourceforge.net/sourceforge/tgwidgets/PlotKit-0.9.1w2-py2.4.egg
Keywords: turbogears.widgets
Platform: UNKNOWN
Classifier: Development Status :: 3 - Alpha
Classifier: Operating System :: OS Independent
Classifier: Programming Language :: Python
Classifier: Topic :: Software Development :: Libraries :: Python Modules
Classifier: Framework :: TurboGears
Classifier: Framework :: TurboGears :: Widgets
